py_schema/__init__.py
py_schema/py_schema.py
py_schema/py_schema_test.py
py_schema-0.12.0.dist-info/LICENSE
py_schema-0.12.0.dist-info/METADATA
py_schema-0.12.0.dist-info/WHEEL
py_schema-0.12.0.dist-info/top_level.txt
py_schema-0.12.0.dist-info/RECORD
