Metadata-Version: 2.1
Name: py-schema
Version: 0.12.0
Summary: A simple and extensible schema validator.
Home-page: https://github.com/benhurott/py_schema
Author: Ben-hur Santos Ott
Author-email: ben-hur@outlook.com
License: UNKNOWN
Platform: UNKNOWN
Classifier: Programming Language :: Python :: 3
Classifier: License :: OSI Approved :: MIT License
Classifier: Operating System :: OS Independent
